{
  "auth": {
    "steprxb088608a": {
      "customAuth": false,
      "dependsOn": [],
      "providerPlugin": "awscloudformation",
      "service": "Cognito",
      "serviceType": "imported"
    }
  },
  "parameters": {
    "AMPLIFY_auth_steprxb088608a_nativeClientId": {
      "usedBy": [
        {
          "category": "auth",
          "resourceName": "steprxb088608a"
        }
      ]
    },
    "AMPLIFY_auth_steprxb088608a_userPoolId": {
      "usedBy": [
        {
          "category": "auth",
          "resourceName": "steprxb088608a"
        }
      ]
    },
    "AMPLIFY_auth_steprxb088608a_userPoolName": {
      "usedBy": [
        {
          "category": "auth",
          "resourceName": "steprxb088608a"
        }
      ]
    },
    "AMPLIFY_auth_steprxb088608a_webClientId": {
      "usedBy": [
        {
          "category": "auth",
          "resourceName": "steprxb088608a"
        }
      ]
    }
  }
}